{"details":[{"idSprinter":"1","birthdate_d":"01","birthdate_m":"01","birthdate_y":"1992","address":"Address Sprinter 1","phone":"0123456789","description":"Lorem ipsum dolor sit amet"},{"idSprinter":"2","birthdate_d":"01","birthdate_m":"01","birthdate_y":"1990","address":"Address Sprinter 2","phone":"0123456789","description":"Lorem ipsum dolor sit amet Lorem ipsum dolor sit ametLorem ipsum dolor sit ametLorem ipsum dolor sit amet\n\nLorem ipsum dolor sit amet Lorem ipsum dolor sit amet Lorem ipsum dolor sit amet"},{"idSprinter":"3","birthdate_d":"01","birthdate_m":"01","birthdate_y":"1990","address":"Address Sprinter 3","phone":"0123456789","description":"Lorem ipsum dolor sit amet"},{"idSprinter":"4","birthdate_d":"01","birthdate_m":"01","birthdate_y":"1990","address":"Address Sprinter 4","phone":"0123456789","description":"Lorem ipsum dolor sit amet"},{"idSprinter":"5","birthdate_d":"01","birthdate_m":"01","birthdate_y":"1990","address":"Address Sprinter 5","phone":"0123456789","description":"Lorem ipsum dolor sit amet"}]}